{
  "@odata.context": "https://api.mlsgrid.com/v2/$metadata#Property",
  "value": [
    {
      "@odata.id": "https://api.mlsgrid.com/v2/Property('NST5153719')",
      "LotSizeArea": 4.6,
      "NST_AgentOwner": "No",
      "InternetAutomatedValuationDisplayYN": false,
      "InternetConsumerCommentYN": false,
      "NST_AssessmentPending": "Unknown",
      "AssociationYN": false,
      "AssociationFee": 0,
      "NST_BuilderRestrict": "Open",
      "BuyerAgencyCompensation": "800.00",
      "BuyerAgencyCompensationType": "$",
      "City": "Motley",
      "PropertyType": "Land",
      "Contingency": "None",
      "CountyOrParish": "Cass",
      "DaysOnMarket": 730,
      "CumulativeDaysOnMarket": 0,
      "DevelopmentStatus": ["Finished Lot(s)"],
      "Directions": "East of Motley on Hwy 210; Left on 65th Ave. SW (Mosquito Creek Rd); 2.4 mi to Left on Otter Run.",
      "InternetAddressDisplayYN": true,
      "InternetEntireListingDisplayYN": true,
      "TransactionBrokerCompensation": "0.0000",
      "TransactionBrokerCompensationType": "%",
      "NST_ForeclosureStatus": "No",
      "NST_FractionalOwnershipYN": "No",
      "RoadFrontageType": ["Township"],
      "NST_Improvements": "None",
      "OriginalEntryTimestamp": "2021-06-24T20:24:04.000Z",
      "NST_InternetOptions": "Fiber Optic",
      "LotSizeDimensions": "248x499x499x478",
      "Inclusions": "Survey,Survey Stakes",
      "LandLeaseAmount": 0,
      "LandLeaseYN": false,
      "NST_LastUpdateDate": "2023-06-25",
      "Latitude": 46.3794698113,
      "NST_LenderOwned": "No",
      "ListAgentKey": "NST89872",
      "ListAgentMlsId": "NST500501308",
      "ListingContractDate": "2021-06-24",
      "ListOfficeKey": "NST16565",
      "ListOfficeName": "Edina Realty, Inc.",
      "ListOfficeMlsId": "NST1469",
      "ListPrice": 35000,
      "Longitude": -94.6248191933,
      "LotSizeUnits": "Acres",
      "ListingId": "NST6015038",
      "SourceSystemName": "RMLS",
      "MapCoordinateSource": "King's Street Atlas",
      "AdditionalParcelsYN": false,
      "OffMarketDate": "2023-06-25",
      "NST_OfficeBoard": "GLAR",
      "ParcelNumber": "245000120",
      "PhotosCount": 1,
      "PostalCity": "Motley",
      "PostalCode": "56466",
      "NST_PotentialShortSale": "No",
      "PublicRemarks": "Nicely wooded, spacious lot in a country setting close to the Brainerd Lakes Area. Additional lots available.",
      "PublicSurveyRange": "31",
      "PublicSurveySection": "31",
      "PublicSurveyTownship": "134",
      "NST_RentalLicenseYN": "No",
      "NST_Restrictions": "Other Covenants",
      "HighSchoolDistrict": "Staples-Motley",
      "NST_SchoolDistrictNumber": "2170",
      "NST_SchoolDistrictPhone": "218-894-2430",
      "StateOrProvince": "MN",
      "StandardStatus": "Expired",
      "StreetName": "Otter Run",
      "StreetNumber": "Lot 2",
      "StreetNumberNumeric": 2,
      "StreetSuffix": "Lane",
      "SubAgencyCompensation": "0.00",
      "SubAgencyCompensationType": "%",
      "SubdivisionName": "Otter View Ridge",
      "NST_TaxWithAssessments": "240.0000",
      "TaxYear": 2022,
      "TaxAnnualAmount": 240,
      "Topography": "Level",
      "Utilities": [
        "None Connected",
        "Electricity Available",
        "Phone Available"
      ],
      "ZoningDescription": "Residential-Single Family",
      "NST_BonusYN": "No",
      "ListingKey": "NST5153719",
      "ModificationTimestamp": "2023-06-25T05:02:03.390Z",
      "PhotosChangeTimestamp": "2022-04-21T16:27:03.444Z",
      "OriginatingSystemName": "northstar",
      "Media": [
        {
          "Order": 1,
          "MediaObjectID": "1",
          "LongDescription": "Lot 2 Aerial",
          "ImageWidth": 1232,
          "ImageHeight": 1148,
          "ImageSizeDescription": "1232x1148",
          "MediaURL": "https://s3.amazonaws.com/mlsgrid/images/28847d7e-cc03-4ada-9bf1-3ec379dc65f7.jpeg",
          "MediaModificationTimestamp": "2022-04-21T16:26:09.718Z",
          "MediaKey": "626185a1a2ab6a5f33a70ad6"
        }
      ],
      "MlgCanView": false
    },
    {
      "@odata.id": "https://api.mlsgrid.com/v2/Property('NST5153760')",
      "LotSizeArea": 4.7,
      "NST_AgentOwner": "No",
      "InternetAutomatedValuationDisplayYN": false,
      "InternetConsumerCommentYN": false,
      "NST_AssessmentPending": "Unknown",
      "AssociationYN": false,
      "AssociationFee": 0,
      "NST_BuilderRestrict": "Open",
      "BuyerAgencyCompensation": "800.00",
      "BuyerAgencyCompensationType": "$",
      "City": "Motley",
      "PropertyType": "Land",
      "Contingency": "None",
      "CountyOrParish": "Cass",
      "DaysOnMarket": 730,
      "CumulativeDaysOnMarket": 0,
      "DevelopmentStatus": ["Finished Lot(s)"],
      "Directions": "East of Motley on Hwy 210; Left on 65th Ave. SW (Mosquito Creek Rd); 2.4 mi to Left on Otter Run.",
      "InternetAddressDisplayYN": true,
      "InternetEntireListingDisplayYN": true,
      "TransactionBrokerCompensation": "0.0000",
      "TransactionBrokerCompensationType": "%",
      "NST_ForeclosureStatus": "No",
      "NST_FractionalOwnershipYN": "No",
      "RoadFrontageType": ["Township"],
      "NST_Improvements": "None",
      "OriginalEntryTimestamp": "2021-06-24T20:38:00.000Z",
      "NST_InternetOptions": "Fiber Optic",
      "LotSizeDimensions": "340x613x75x814",
      "Inclusions": "Survey,Survey Stakes",
      "LandLeaseAmount": 0,
      "LandLeaseYN": false,
      "NST_LastUpdateDate": "2023-06-25",
      "Latitude": 46.3771142196,
      "NST_LenderOwned": "No",
      "ListAgentKey": "NST89872",
      "ListAgentMlsId": "NST500501308",
      "ListingContractDate": "2021-06-24",
      "ListOfficeKey": "NST16565",
      "ListOfficeName": "Edina Realty, Inc.",
      "ListOfficeMlsId": "NST1469",
      "ListPrice": 35000,
      "Longitude": -94.6270399104,
      "LotFeatures": ["Tree Coverage - Light"],
      "LotSizeUnits": "Acres",
      "ListingId": "NST6015079",
      "SourceSystemName": "RMLS",
      "MapCoordinateSource": "King's Street Atlas",
      "AdditionalParcelsYN": false,
      "OffMarketDate": "2023-06-25",
      "NST_OfficeBoard": "GLAR",
      "ParcelNumber": "245000180",
      "PhotosCount": 1,
      "PostalCity": "Motley",
      "PostalCode": "56466",
      "NST_PotentialShortSale": "No",
      "PublicRemarks": "Nicely wooded lot available in a private, country setting close to Brainerd. Additional lots available.",
      "PublicSurveyRange": "31",
      "PublicSurveySection": "31",
      "PublicSurveyTownship": "134",
      "NST_RentalLicenseYN": "No",
      "NST_Restrictions": "Other Covenants",
      "HighSchoolDistrict": "Staples-Motley",
      "NST_SchoolDistrictNumber": "2170",
      "NST_SchoolDistrictPhone": "218-894-2430",
      "StateOrProvince": "MN",
      "StandardStatus": "Expired",
      "StreetDirSuffix": "SW",
      "StreetName": "Otter Run",
      "StreetNumber": "Lot 8",
      "StreetNumberNumeric": 8,
      "StreetSuffix": "Lane",
      "SubAgencyCompensation": "0.00",
      "SubAgencyCompensationType": "%",
      "SubdivisionName": "Otter View Ridge",
      "NST_TaxWithAssessments": "240.0000",
      "TaxYear": 2023,
      "TaxAnnualAmount": 240,
      "Topography": "Level",
      "Utilities": [
        "None Connected",
        "Electricity Available",
        "Phone Available"
      ],
      "ZoningDescription": "Residential-Single Family",
      "NST_BonusYN": "No",
      "ListingKey": "NST5153760",
      "ModificationTimestamp": "2023-06-25T05:02:03.471Z",
      "OriginatingSystemName": "northstar",
      "Media": [
        {
          "Order": 1,
          "MediaObjectID": "1",
          "LongDescription": "Scan0032",
          "ImageWidth": 2006,
          "ImageHeight": 1388,
          "ImageSizeDescription": "2006x1388",
          "MediaURL": "https://s3.amazonaws.com/mlsgrid/images/60c69b7a-153b-4666-a549-490fd902a25f.jpeg",
          "MediaModificationTimestamp": "2022-02-04T15:40:36.818Z",
          "MediaKey": "61fd48f43c4ef8042342862d"
        }
      ],
      "PhotosChangeTimestamp": "2022-02-04T15:41:03.416Z",
      "MlgCanView": false
    },
    {
      "@odata.id": "https://api.mlsgrid.com/v2/Property('NST5153773')",
      "LotSizeArea": 4.7,
      "NST_AgentOwner": "No",
      "InternetAutomatedValuationDisplayYN": false,
      "InternetConsumerCommentYN": false,
      "NST_AssessmentPending": "Unknown",
      "AssociationYN": false,
      "AssociationFee": 0,
      "NST_BuilderRestrict": "Open",
      "BuyerAgencyCompensation": "800.00",
      "BuyerAgencyCompensationType": "$",
      "City": "Motley",
      "PropertyType": "Land",
      "Contingency": "None",
      "CountyOrParish": "Cass",
      "DaysOnMarket": 730,
      "CumulativeDaysOnMarket": 0,
      "DevelopmentStatus": ["Finished Lot(s)"],
      "Directions": "East of Motley on Hwy 210; Left on 65th Ave. SW (Mosquito Creek Rd); 2.4 mi to Left on Otter Run.",
      "InternetAddressDisplayYN": true,
      "InternetEntireListingDisplayYN": true,
      "TransactionBrokerCompensation": "0.0000",
      "TransactionBrokerCompensationType": "%",
      "NST_ForeclosureStatus": "No",
      "NST_FractionalOwnershipYN": "No",
      "RoadFrontageType": ["Township"],
      "NST_Improvements": "None",
      "OriginalEntryTimestamp": "2021-06-24T20:46:29.000Z",
      "NST_InternetOptions": "Fiber Optic",
      "LotSizeDimensions": "733x661x1x661",
      "Inclusions": "Survey,Survey Stakes",
      "LandLeaseAmount": 0,
      "LandLeaseYN": false,
      "NST_LastUpdateDate": "2023-06-25",
      "Latitude": 46.3780194261,
      "NST_LenderOwned": "No",
      "ListAgentKey": "NST89872",
      "ListAgentMlsId": "NST500501308",
      "ListingContractDate": "2021-06-24",
      "ListOfficeKey": "NST16565",
      "ListOfficeName": "Edina Realty, Inc.",
      "ListOfficeMlsId": "NST1469",
      "ListPrice": 35000,
      "Longitude": -94.6260104193,
      "LotFeatures": ["Tree Coverage - Medium"],
      "LotSizeUnits": "Acres",
      "ListingId": "NST6015092",
      "SourceSystemName": "RMLS",
      "MapCoordinateSource": "King's Street Atlas",
      "AdditionalParcelsYN": false,
      "OffMarketDate": "2023-06-25",
      "NST_OfficeBoard": "GLAR",
      "ParcelNumber": "245000190",
      "PhotosCount": 1,
      "PostalCity": "Motley",
      "PostalCode": "56466",
      "NST_PotentialShortSale": "No",
      "PublicRemarks": "Nicely wooded lot available in a private, country setting close to Brainerd.  Additional lots available.",
      "PublicSurveyRange": "31",
      "PublicSurveySection": "31",
      "PublicSurveyTownship": "134",
      "NST_RentalLicenseYN": "No",
      "NST_Restrictions": "Other Covenants",
      "HighSchoolDistrict": "Staples-Motley",
      "NST_SchoolDistrictNumber": "2170",
      "NST_SchoolDistrictPhone": "218-894-2430",
      "StateOrProvince": "MN",
      "StandardStatus": "Expired",
      "StreetDirSuffix": "SW",
      "StreetName": "Otter Run",
      "StreetNumber": "Lot 9",
      "StreetNumberNumeric": 9,
      "StreetSuffix": "Lane",
      "SubAgencyCompensation": "0.00",
      "SubAgencyCompensationType": "%",
      "SubdivisionName": "Otter View Ridge",
      "NST_TaxWithAssessments": "240.0000",
      "TaxYear": 2023,
      "TaxAnnualAmount": 240,
      "Topography": "Level,Low Land,Rolling",
      "Utilities": [
        "None Connected",
        "Electricity Available",
        "Phone Available"
      ],
      "ZoningDescription": "Residential-Single Family",
      "NST_BonusYN": "No",
      "ListingKey": "NST5153773",
      "ModificationTimestamp": "2023-06-25T05:02:03.498Z",
      "PhotosChangeTimestamp": "2022-04-21T16:29:03.158Z",
      "OriginatingSystemName": "northstar",
      "Media": [
        {
          "Order": 1,
          "MediaObjectID": "1",
          "LongDescription": "Scan0034",
          "ImageWidth": 2039,
          "ImageHeight": 1342,
          "ImageSizeDescription": "2039x1342",
          "MediaURL": "https://s3.amazonaws.com/mlsgrid/images/fb015463-6ee9-4c37-9274-b14ead88cf2e.jpeg",
          "MediaModificationTimestamp": "2022-04-21T16:28:10.043Z",
          "MediaKey": "6261861aa2ab6a5f33a70b62"
        }
      ],
      "MlgCanView": false
    },
    {
      "@odata.id": "https://api.mlsgrid.com/v2/Property('NST5153911')",
      "LotSizeArea": 2.73,
      "NST_AgentOwner": "No",
      "InternetAutomatedValuationDisplayYN": false,
      "InternetConsumerCommentYN": false,
      "NST_AssessmentPending": "Unknown",
      "AssociationYN": false,
      "AssociationFee": 0,
      "NST_BuilderRestrict": "Open",
      "BuyerAgencyCompensation": "800.00",
      "BuyerAgencyCompensationType": "$",
      "City": "Motley",
      "PropertyType": "Land",
      "Contingency": "None",
      "CountyOrParish": "Todd",
      "DaysOnMarket": 729,
      "CumulativeDaysOnMarket": 0,
      "DevelopmentStatus": ["Finished Lot(s)"],
      "Directions": "From Motley, Hwy 10 West to Right on Morrison Line Road.",
      "InternetAddressDisplayYN": true,
      "InternetEntireListingDisplayYN": true,
      "TransactionBrokerCompensation": "0.0000",
      "TransactionBrokerCompensationType": "%",
      "NST_ForeclosureStatus": "No",
      "NST_FractionalOwnershipYN": "No",
      "RoadFrontageType": ["Township"],
      "NST_Improvements": "Paved Streets",
      "OriginalEntryTimestamp": "2021-06-25T12:17:33.000Z",
      "LotSizeDimensions": "270x433x270x433",
      "Inclusions": "Platted,Survey,Survey Stakes",
      "LandLeaseAmount": 0,
      "LandLeaseYN": false,
      "NST_LastUpdateDate": "2023-06-25",
      "Latitude": 46.3435744404,
      "NST_LenderOwned": "No",
      "ListAgentKey": "NST89872",
      "ListAgentMlsId": "NST500501308",
      "ListingContractDate": "2021-06-25",
      "ListOfficeKey": "NST16565",
      "ListOfficeName": "Edina Realty, Inc.",
      "ListOfficeMlsId": "NST1469",
      "ListPrice": 40000,
      "Longitude": -94.6543641559,
      "LotSizeUnits": "Acres",
      "ListingId": "NST6015230",
      "SourceSystemName": "RMLS",
      "MapCoordinateSource": "King's Street Atlas",
      "AdditionalParcelsYN": false,
      "OffMarketDate": "2023-06-25",
      "NST_OfficeBoard": "GLAR",
      "ParcelNumber": "250057500",
      "PhotosCount": 1,
      "PostalCity": "Motley",
      "PostalCode": "56466",
      "NST_PotentialShortSale": "No",
      "PublicRemarks": "This residential development offers large, buildable lots and a great location close to town!",
      "NST_RentalLicenseYN": "No",
      "NST_Restrictions": "Other Covenants",
      "HighSchoolDistrict": "Staples-Motley",
      "NST_SchoolDistrictNumber": "2170",
      "NST_SchoolDistrictPhone": "218-894-2430",
      "StateOrProvince": "MN",
      "StandardStatus": "Expired",
      "StreetName": "Morrison Line",
      "StreetNumber": "Lot 9",
      "StreetNumberNumeric": 9,
      "StreetSuffix": "Road",
      "SubAgencyCompensation": "0.00",
      "SubAgencyCompensationType": "%",
      "SubdivisionName": "Oxbow Estates",
      "NST_TaxWithAssessments": "346.0000",
      "TaxYear": 2020,
      "TaxAnnualAmount": 346,
      "Topography": "Level",
      "Utilities": [
        "None Connected",
        "Electricity Available",
        "Natural Gas Available"
      ],
      "ZoningDescription": "Residential-Single Family",
      "NST_BonusYN": "No",
      "ListingKey": "NST5153911",
      "ModificationTimestamp": "2023-06-25T05:02:03.529Z",
      "PhotosChangeTimestamp": "2022-05-14T20:37:03.318Z",
      "OriginatingSystemName": "northstar",
      "Media": [
        {
          "Order": 1,
          "MediaObjectID": "1",
          "LongDescription": "Morrison Line Road Lot 9",
          "ImageWidth": 1454,
          "ImageHeight": 1464,
          "ImageSizeDescription": "1454x1464",
          "MediaURL": "https://s3.amazonaws.com/mlsgrid/images/eb0a48d8-8505-4764-9eb8-8b974e6fd15c.jpeg",
          "MediaModificationTimestamp": "2022-05-14T20:36:16.644Z",
          "MediaKey": "628012c0d1a6e603c9d9274b"
        }
      ],
      "MlgCanView": false
    },
    {
      "@odata.id": "https://api.mlsgrid.com/v2/Property('NST5153915')",
      "LotSizeArea": 2.73,
      "NST_AgentOwner": "No",
      "InternetAutomatedValuationDisplayYN": false,
      "InternetConsumerCommentYN": false,
      "NST_AssessmentPending": "Unknown",
      "AssociationYN": false,
      "AssociationFee": 0,
      "NST_BuilderRestrict": "Open",
      "BuyerAgencyCompensation": "800.00",
      "BuyerAgencyCompensationType": "$",
      "City": "Motley",
      "PropertyType": "Land",
      "Contingency": "None",
      "CountyOrParish": "Todd",
      "DaysOnMarket": 729,
      "CumulativeDaysOnMarket": 0,
      "DevelopmentStatus": ["Finished Lot(s)"],
      "Directions": "From Motley, West on Hwy 10 to Right on Morrison Line Road.",
      "InternetAddressDisplayYN": true,
      "InternetEntireListingDisplayYN": true,
      "TransactionBrokerCompensation": "0.0000",
      "TransactionBrokerCompensationType": "%",
      "NST_ForeclosureStatus": "No",
      "NST_FractionalOwnershipYN": "No",
      "RoadFrontageType": ["Township"],
      "NST_Improvements": "Paved Streets",
      "OriginalEntryTimestamp": "2021-06-25T12:34:11.000Z",
      "LotSizeDimensions": "275x433x275x433",
      "Inclusions": "Platted,Survey,Survey Stakes",
      "LandLeaseAmount": 0,
      "LandLeaseYN": false,
      "NST_LastUpdateDate": "2023-06-25",
      "Latitude": 46.3443284478,
      "NST_LenderOwned": "No",
      "ListAgentKey": "NST89872",
      "ListAgentMlsId": "NST500501308",
      "ListingContractDate": "2021-06-25",
      "ListOfficeKey": "NST16565",
      "ListOfficeName": "Edina Realty, Inc.",
      "ListOfficeMlsId": "NST1469",
      "ListPrice": 40000,
      "Longitude": -94.6543670543,
      "LotSizeUnits": "Acres",
      "ListingId": "NST6015234",
      "SourceSystemName": "RMLS",
      "MapCoordinateSource": "King's Street Atlas",
      "AdditionalParcelsYN": false,
      "OffMarketDate": "2023-06-25",
      "NST_OfficeBoard": "GLAR",
      "ParcelNumber": "250057600",
      "PhotosCount": 1,
      "PostalCity": "Motley",
      "PostalCode": "56466",
      "NST_PotentialShortSale": "No",
      "PublicRemarks": "This residential development offers large, buildable lots and a great location close to town!",
      "NST_RentalLicenseYN": "No",
      "NST_Restrictions": "Other Covenants",
      "HighSchoolDistrict": "Staples-Motley",
      "NST_SchoolDistrictNumber": "2170",
      "NST_SchoolDistrictPhone": "218-894-2430",
      "StateOrProvince": "MN",
      "StandardStatus": "Expired",
      "StreetName": "Morrison Line",
      "StreetNumber": "Lot 10",
      "StreetNumberNumeric": 10,
      "StreetSuffix": "Road",
      "SubAgencyCompensation": "0.00",
      "SubAgencyCompensationType": "%",
      "SubdivisionName": "Oxbow Estates",
      "NST_TaxWithAssessments": "346.0000",
      "TaxYear": 2020,
      "TaxAnnualAmount": 346,
      "Topography": "Level",
      "Utilities": [
        "None Connected",
        "Electricity Available",
        "Natural Gas Available"
      ],
      "ZoningDescription": "Residential-Single Family",
      "NST_BonusYN": "No",
      "ListingKey": "NST5153915",
      "ModificationTimestamp": "2023-06-25T05:02:03.552Z",
      "PhotosChangeTimestamp": "2022-05-14T20:37:03.335Z",
      "OriginatingSystemName": "northstar",
      "Media": [
        {
          "Order": 1,
          "MediaObjectID": "1",
          "LongDescription": "Morrison Line Road Lot 10",
          "ImageWidth": 1482,
          "ImageHeight": 1389,
          "ImageSizeDescription": "1482x1389",
          "MediaURL": "https://s3.amazonaws.com/mlsgrid/images/d0f39e72-2f2b-4e7f-91cb-919a637929ea.jpeg",
          "MediaModificationTimestamp": "2022-05-14T20:36:17.454Z",
          "MediaKey": "628012c1d1a6e603c9d9274c"
        }
      ],
      "MlgCanView": false
    },
    {
      "@odata.id": "https://api.mlsgrid.com/v2/Property('NST5153994')",
      "LotSizeArea": 2.83,
      "NST_AgentOwner": "No",
      "InternetAutomatedValuationDisplayYN": false,
      "InternetConsumerCommentYN": false,
      "NST_AssessmentPending": "No",
      "AssociationYN": false,
      "AssociationFee": 0,
      "NST_BuilderRestrict": "Open",
      "BuyerAgencyCompensation": "800.00",
      "BuyerAgencyCompensationType": "$",
      "City": "Motley",
      "PropertyType": "Land",
      "Contingency": "None",
      "CountyOrParish": "Todd",
      "DaysOnMarket": 729,
      "CumulativeDaysOnMarket": 0,
      "DevelopmentStatus": ["Finished Lot(s)"],
      "Directions": "From Motley, West on Hwy 10 to Right on Morrison Line Road.",
      "InternetAddressDisplayYN": true,
      "InternetEntireListingDisplayYN": true,
      "TransactionBrokerCompensation": "0.0000",
      "TransactionBrokerCompensationType": "%",
      "NST_ForeclosureStatus": "No",
      "NST_FractionalOwnershipYN": "No",
      "RoadFrontageType": ["Township"],
      "NST_Improvements": "Paved Streets",
      "OriginalEntryTimestamp": "2021-06-25T14:21:11.000Z",
      "LotSizeDimensions": "239x518x243x470",
      "Inclusions": "Platted,Survey,Survey Stakes",
      "LandLeaseAmount": 0,
      "LandLeaseYN": false,
      "NST_LastUpdateDate": "2023-06-25",
      "Latitude": 46.3415468127,
      "NST_LenderOwned": "No",
      "ListAgentKey": "NST89872",
      "ListAgentMlsId": "NST500501308",
      "ListingContractDate": "2021-06-25",
      "ListOfficeKey": "NST16565",
      "ListOfficeName": "Edina Realty, Inc.",
      "ListOfficeMlsId": "NST1469",
      "ListPrice": 40000,
      "Longitude": -94.6566895221,
      "LotSizeUnits": "Acres",
      "ListingId": "NST6015313",
      "SourceSystemName": "RMLS",
      "MapCoordinateSource": "King's Street Atlas",
      "AdditionalParcelsYN": false,
      "OffMarketDate": "2023-06-25",
      "NST_OfficeBoard": "GLAR",
      "ParcelNumber": "250058300",
      "PhotosCount": 1,
      "PostalCity": "Motley",
      "PostalCode": "56466",
      "NST_PotentialShortSale": "No",
      "PublicRemarks": "This residential development offers large, buildable lots and a great location close to town!",
      "NST_RentalLicenseYN": "No",
      "NST_Restrictions": "Other Covenants",
      "HighSchoolDistrict": "Staples-Motley",
      "NST_SchoolDistrictNumber": "2170",
      "NST_SchoolDistrictPhone": "218-894-2430",
      "StateOrProvince": "MN",
      "StandardStatus": "Expired",
      "StreetName": "Twin Oaks",
      "StreetNumber": "Lot 2 Blk 3",
      "StreetNumberNumeric": 2,
      "StreetSuffix": "Loop",
      "SubAgencyCompensation": "0.00",
      "SubAgencyCompensationType": "%",
      "SubdivisionName": "Oxbow Estates",
      "NST_TaxWithAssessments": "360.0000",
      "TaxYear": 2020,
      "TaxAnnualAmount": 360,
      "Topography": "Level",
      "Utilities": [
        "None Connected",
        "Electricity Available",
        "Natural Gas Available"
      ],
      "ZoningDescription": "Residential-Single Family",
      "NST_BonusYN": "No",
      "ListingKey": "NST5153994",
      "ModificationTimestamp": "2023-06-25T05:02:03.566Z",
      "PhotosChangeTimestamp": "2022-05-14T20:33:03.341Z",
      "OriginatingSystemName": "northstar",
      "Media": [
        {
          "Order": 1,
          "MediaObjectID": "1",
          "LongDescription": "Twin Oaks Loop Lot 2 Blk 3",
          "ImageWidth": 1444,
          "ImageHeight": 1500,
          "ImageSizeDescription": "1444x1500",
          "MediaURL": "https://s3.amazonaws.com/mlsgrid/images/a165c555-9ec1-4f60-8b3a-cda3d83ded88.jpeg",
          "MediaModificationTimestamp": "2022-05-14T20:32:25.234Z",
          "MediaKey": "628011d927d73d7935caa4e9"
        }
      ],
      "MlgCanView": false
    },
    {
      "@odata.id": "https://api.mlsgrid.com/v2/Property('NST5154590')",
      "LotSizeArea": 3.4,
      "NST_AgentOwner": "No",
      "InternetAutomatedValuationDisplayYN": false,
      "InternetConsumerCommentYN": false,
      "NST_AssessmentPending": "No",
      "AssociationYN": false,
      "AssociationFee": 0,
      "NST_BuilderRestrict": "Open",
      "BuyerAgencyCompensation": "800.00",
      "BuyerAgencyCompensationType": "$",
      "City": "Motley",
      "PropertyType": "Land",
      "Contingency": "None",
      "CountyOrParish": "Todd",
      "DaysOnMarket": 729,
      "CumulativeDaysOnMarket": 0,
      "DevelopmentStatus": ["Finished Lot(s)"],
      "Directions": "From Motley, West on Hwy 10 to Right on Morrison Line Road.",
      "InternetAddressDisplayYN": true,
      "InternetEntireListingDisplayYN": true,
      "TransactionBrokerCompensation": "0.0000",
      "TransactionBrokerCompensationType": "%",
      "NST_ForeclosureStatus": "No",
      "NST_FractionalOwnershipYN": "No",
      "RoadFrontageType": ["Township"],
      "NST_Improvements": "Paved Streets",
      "OriginalEntryTimestamp": "2021-06-26T13:21:57.000Z",
      "LotSizeDimensions": "356x434x400x431",
      "Inclusions": "Platted,Survey,Survey Stakes",
      "LandLeaseAmount": 0,
      "LandLeaseYN": false,
      "NST_LastUpdateDate": "2023-06-25",
      "Latitude": 46.341479725,
      "NST_LenderOwned": "No",
      "ListAgentKey": "NST89872",
      "ListAgentMlsId": "NST500501308",
      "ListingContractDate": "2021-06-25",
      "ListOfficeKey": "NST16565",
      "ListOfficeName": "Edina Realty, Inc.",
      "ListOfficeMlsId": "NST1469",
      "ListPrice": 40000,
      "Longitude": -94.6607630789,
      "LotSizeUnits": "Acres",
      "ListingId": "NST6015909",
      "SourceSystemName": "RMLS",
      "MapCoordinateSource": "King's Street Atlas",
      "AdditionalParcelsYN": false,
      "OffMarketDate": "2023-06-25",
      "NST_OfficeBoard": "GLAR",
      "ParcelNumber": "250058600",
      "PhotosCount": 1,
      "PostalCity": "Motley",
      "PostalCode": "56466",
      "NST_PotentialShortSale": "No",
      "PublicRemarks": "This residential development offers large, buildable lots and a great location close to town!",
      "NST_RentalLicenseYN": "No",
      "NST_Restrictions": "Other Covenants",
      "HighSchoolDistrict": "Staples-Motley",
      "NST_SchoolDistrictNumber": "2170",
      "NST_SchoolDistrictPhone": "218-894-2430",
      "StateOrProvince": "MN",
      "StandardStatus": "Expired",
      "StreetDirSuffix": "W",
      "StreetName": "Twin Oaks",
      "StreetNumber": "Lot 2 Blk 1",
      "StreetNumberNumeric": 2,
      "StreetSuffix": "Loop",
      "SubAgencyCompensation": "0.00",
      "SubAgencyCompensationType": "%",
      "SubdivisionName": "Oxbow Estates West",
      "NST_TaxWithAssessments": "430.0000",
      "TaxYear": 2020,
      "TaxAnnualAmount": 430,
      "Topography": "Level",
      "Utilities": ["None Connected", "Electricity Available"],
      "ZoningDescription": "Residential-Single Family",
      "NST_BonusYN": "No",
      "ListingKey": "NST5154590",
      "ModificationTimestamp": "2023-06-25T05:02:03.581Z",
      "OriginatingSystemName": "northstar",
      "Media": [
        {
          "Order": 1,
          "MediaObjectID": "1",
          "LongDescription": "Twin Oaks Loop W. Lot 2 Blk 1",
          "ImageWidth": 1454,
          "ImageHeight": 1597,
          "ImageSizeDescription": "1454x1597",
          "MediaURL": "https://s3.amazonaws.com/mlsgrid/images/7ebb30e7-9a7c-435f-944b-df114d9e336e.jpeg",
          "MediaModificationTimestamp": "2022-03-18T21:17:36.044Z",
          "MediaKey": "6234f6f0cc18517005a61d3a"
        }
      ],
      "PhotosChangeTimestamp": "2022-03-18T21:18:03.431Z",
      "MlgCanView": false
    },
    {
      "@odata.id": "https://api.mlsgrid.com/v2/Property('NST5154026')",
      "LotSizeArea": 2.55,
      "NST_AgentOwner": "No",
      "InternetAutomatedValuationDisplayYN": false,
      "InternetConsumerCommentYN": false,
      "NST_AssessmentPending": "No",
      "AssociationYN": false,
      "AssociationFee": 0,
      "NST_BuilderRestrict": "Open",
      "BuyerAgencyCompensation": "800.00",
      "BuyerAgencyCompensationType": "$",
      "City": "Motley",
      "PropertyType": "Land",
      "Contingency": "None",
      "CountyOrParish": "Todd",
      "DaysOnMarket": 729,
      "CumulativeDaysOnMarket": 0,
      "DevelopmentStatus": ["Finished Lot(s)"],
      "Directions": "From Motley, West on Hwy 10 to Right on Morrison Line Road.",
      "InternetAddressDisplayYN": true,
      "InternetEntireListingDisplayYN": true,
      "TransactionBrokerCompensation": "0.0000",
      "TransactionBrokerCompensationType": "%",
      "NST_ForeclosureStatus": "No",
      "NST_FractionalOwnershipYN": "No",
      "RoadFrontageType": ["Township"],
      "NST_Improvements": "Paved Streets",
      "OriginalEntryTimestamp": "2021-06-26T16:40:44.000Z",
      "LotSizeDimensions": "268x375x268x403",
      "Inclusions": "Platted,Survey,Survey Stakes",
      "LandLeaseAmount": 0,
      "LandLeaseYN": false,
      "NST_LastUpdateDate": "2023-06-25",
      "Latitude": 46.3437040184,
      "NST_LenderOwned": "No",
      "ListAgentKey": "NST89872",
      "ListAgentMlsId": "NST500501308",
      "ListingContractDate": "2021-06-25",
      "ListOfficeKey": "NST16565",
      "ListOfficeName": "Edina Realty, Inc.",
      "ListOfficeMlsId": "NST1469",
      "ListPrice": 40000,
      "Longitude": -94.6578532664,
      "LotSizeUnits": "Acres",
      "ListingId": "NST6015345",
      "SourceSystemName": "RMLS",
      "MapCoordinateSource": "King's Street Atlas",
      "AdditionalParcelsYN": false,
      "OffMarketDate": "2023-06-25",
      "NST_OfficeBoard": "GLAR",
      "ParcelNumber": "250056800",
      "PhotosCount": 1,
      "PostalCity": "Motley",
      "PostalCode": "56466",
      "NST_PotentialShortSale": "No",
      "PublicRemarks": "This residential development offers large, buildable lots and a great location close to all of towns amenities!",
      "NST_RentalLicenseYN": "No",
      "NST_Restrictions": "Other Covenants",
      "HighSchoolDistrict": "Staples-Motley",
      "NST_SchoolDistrictNumber": "2170",
      "NST_SchoolDistrictPhone": "218-894-2430",
      "StateOrProvince": "MN",
      "StandardStatus": "Expired",
      "StreetName": "Twilight",
      "StreetNumber": "Lot 2",
      "StreetNumberNumeric": 2,
      "StreetSuffix": "Trail",
      "SubAgencyCompensation": "0.00",
      "SubAgencyCompensationType": "%",
      "SubdivisionName": "Oxbow Estates",
      "NST_TaxWithAssessments": "324.0000",
      "TaxYear": 2020,
      "TaxAnnualAmount": 324,
      "Topography": "Level",
      "Utilities": [
        "None Connected",
        "Electricity Available",
        "Natural Gas Available"
      ],
      "ZoningDescription": "Residential-Single Family",
      "NST_BonusYN": "No",
      "ListingKey": "NST5154026",
      "ModificationTimestamp": "2023-06-25T05:02:03.595Z",
      "PhotosChangeTimestamp": "2022-05-14T20:35:03.496Z",
      "OriginatingSystemName": "northstar",
      "Media": [
        {
          "Order": 1,
          "MediaObjectID": "1",
          "LongDescription": "Twilight Trail Lot 2",
          "ImageWidth": 1456,
          "ImageHeight": 1527,
          "ImageSizeDescription": "1456x1527",
          "MediaURL": "https://s3.amazonaws.com/mlsgrid/images/145b7a1b-0eeb-4dbf-b2eb-1800ccf3b0f2.jpeg",
          "MediaModificationTimestamp": "2022-05-14T20:34:25.301Z",
          "MediaKey": "6280125127d73d7935caa53d"
        }
      ],
      "MlgCanView": false
    },
    {
      "@odata.id": "https://api.mlsgrid.com/v2/Property('NST5153982')",
      "LotSizeArea": 3.75,
      "NST_AgentOwner": "No",
      "InternetAutomatedValuationDisplayYN": true,
      "InternetConsumerCommentYN": true,
      "NST_AssessmentPending": "No",
      "AssociationYN": false,
      "AssociationFee": 0,
      "NST_BuilderRestrict": "Open",
      "BuyerAgencyCompensation": "800.00",
      "BuyerAgencyCompensationType": "$",
      "City": "Motley",
      "PropertyType": "Land",
      "Contingency": "None",
      "CountyOrParish": "Todd",
      "DaysOnMarket": 729,
      "CumulativeDaysOnMarket": 0,
      "DevelopmentStatus": ["Finished Lot(s)"],
      "Directions": "From Motley, West on Hwy 10 to Right on Morrison Line Road.",
      "InternetAddressDisplayYN": true,
      "InternetEntireListingDisplayYN": true,
      "TransactionBrokerCompensation": "0.0000",
      "TransactionBrokerCompensationType": "%",
      "NST_ForeclosureStatus": "No",
      "NST_FractionalOwnershipYN": "No",
      "RoadFrontageType": ["Township"],
      "NST_Improvements": "Paved Streets",
      "OriginalEntryTimestamp": "2021-06-26T16:41:02.000Z",
      "LotSizeDimensions": "295x500x303x518",
      "Inclusions": "Platted,Survey,Survey Stakes",
      "LandLeaseAmount": 0,
      "LandLeaseYN": false,
      "NST_LastUpdateDate": "2023-06-25",
      "Latitude": 46.3416110862,
      "NST_LenderOwned": "No",
      "ListAgentKey": "NST89872",
      "ListAgentMlsId": "NST500501308",
      "ListingContractDate": "2021-06-25",
      "ListOfficeKey": "NST16565",
      "ListOfficeName": "Edina Realty, Inc.",
      "ListOfficeMlsId": "NST1469",
      "ListPrice": 40000,
      "Longitude": -94.6577907197,
      "LotSizeUnits": "Acres",
      "ListingId": "NST6015301",
      "SourceSystemName": "RMLS",
      "MapCoordinateSource": "King's Street Atlas",
      "AdditionalParcelsYN": false,
      "OffMarketDate": "2023-06-25",
      "NST_OfficeBoard": "GLAR",
      "ParcelNumber": "250058200",
      "PhotosCount": 1,
      "PostalCity": "Motley",
      "PostalCode": "56466",
      "NST_PotentialShortSale": "No",
      "PublicRemarks": "This residential development offers large, buildable lots and a great location close to all of towns amenities!",
      "NST_RentalLicenseYN": "No",
      "NST_Restrictions": "Other Covenants",
      "HighSchoolDistrict": "Staples-Motley",
      "NST_SchoolDistrictNumber": "2170",
      "NST_SchoolDistrictPhone": "218-894-2430",
      "StateOrProvince": "MN",
      "StandardStatus": "Expired",
      "StreetName": "Twin Oaks",
      "StreetNumber": "Lot 1 Blk 3",
      "StreetNumberNumeric": 1,
      "StreetSuffix": "Loop",
      "SubAgencyCompensation": "0.00",
      "SubAgencyCompensationType": "%",
      "SubdivisionName": "Oxbow Estates",
      "NST_TaxWithAssessments": "474.0000",
      "TaxYear": 2020,
      "TaxAnnualAmount": 474,
      "Topography": "Level",
      "Utilities": [
        "None Connected",
        "Electricity Available",
        "Natural Gas Available"
      ],
      "ZoningDescription": "Residential-Single Family",
      "NST_BonusYN": "No",
      "ListingKey": "NST5153982",
      "ModificationTimestamp": "2023-06-25T05:02:03.610Z",
      "PhotosChangeTimestamp": "2022-05-14T20:34:03.293Z",
      "OriginatingSystemName": "northstar",
      "Media": [
        {
          "Order": 1,
          "MediaObjectID": "1",
          "LongDescription": "Twin Oaks Loop Lot 1 Blk 3",
          "ImageWidth": 1460,
          "ImageHeight": 1563,
          "ImageSizeDescription": "1460x1563",
          "MediaURL": "https://s3.amazonaws.com/mlsgrid/images/fbdbf518-3f4a-45b3-b894-8241e2a32c67.jpeg",
          "MediaModificationTimestamp": "2022-05-14T20:33:15.196Z",
          "MediaKey": "6280120ba015fe1bf85fde77"
        }
      ],
      "MlgCanView": false
    },
    {
      "@odata.id": "https://api.mlsgrid.com/v2/Property('NST5154644')",
      "LotSizeArea": 2.59,
      "NST_AgentOwner": "No",
      "InternetAutomatedValuationDisplayYN": false,
      "InternetConsumerCommentYN": false,
      "NST_AssessmentPending": "No",
      "AssociationYN": false,
      "AssociationFee": 0,
      "NST_BuilderRestrict": "Open",
      "BuyerAgencyCompensation": "800.00",
      "BuyerAgencyCompensationType": "$",
      "City": "Motley",
      "PropertyType": "Land",
      "Contingency": "None",
      "CountyOrParish": "Todd",
      "DaysOnMarket": 729,
      "CumulativeDaysOnMarket": 0,
      "DevelopmentStatus": ["Finished Lot(s)"],
      "Directions": "From Motley, West on Hwy 10 to Right on Morrison Line Road.",
      "InternetAddressDisplayYN": true,
      "InternetEntireListingDisplayYN": true,
      "TransactionBrokerCompensation": "0.0000",
      "TransactionBrokerCompensationType": "%",
      "NST_ForeclosureStatus": "No",
      "NST_FractionalOwnershipYN": "No",
      "RoadFrontageType": ["Township"],
      "NST_Improvements": "Paved Streets",
      "OriginalEntryTimestamp": "2021-06-26T17:04:04.000Z",
      "LotSizeDimensions": "292x537x248x395",
      "Inclusions": "Platted,Survey,Survey Stakes",
      "LandLeaseAmount": 0,
      "LandLeaseYN": false,
      "NST_LastUpdateDate": "2023-06-25",
      "Latitude": 46.3424078585,
      "NST_LenderOwned": "No",
      "ListAgentKey": "NST89872",
      "ListAgentMlsId": "NST500501308",
      "ListingContractDate": "2021-06-25",
      "ListOfficeKey": "NST16565",
      "ListOfficeName": "Edina Realty, Inc.",
      "ListOfficeMlsId": "NST1469",
      "ListPrice": 40000,
      "Longitude": -94.6630614981,
      "LotSizeUnits": "Acres",
      "ListingId": "NST6015963",
      "SourceSystemName": "RMLS",
      "MapCoordinateSource": "King's Street Atlas",
      "AdditionalParcelsYN": false,
      "OffMarketDate": "2023-06-25",
      "NST_OfficeBoard": "GLAR",
      "ParcelNumber": "250058700",
      "PhotosCount": 1,
      "PostalCity": "Motley",
      "PostalCode": "56466",
      "NST_PotentialShortSale": "No",
      "PublicRemarks": "This residential development offers large, buildable lots and a great location close to town!",
      "NST_RentalLicenseYN": "No",
      "NST_Restrictions": "Other Covenants",
      "HighSchoolDistrict": "Staples-Motley",
      "NST_SchoolDistrictNumber": "2170",
      "NST_SchoolDistrictPhone": "218-894-2430",
      "StateOrProvince": "MN",
      "StandardStatus": "Expired",
      "StreetDirSuffix": "W",
      "StreetName": "Twin Oaks",
      "StreetNumber": "Lot 1 Blk 2",
      "StreetNumberNumeric": 1,
      "StreetSuffix": "Loop",
      "SubAgencyCompensation": "0.00",
      "SubAgencyCompensationType": "%",
      "SubdivisionName": "Oxbow Estates West",
      "NST_TaxWithAssessments": "328.0000",
      "TaxYear": 2020,
      "TaxAnnualAmount": 328,
      "Topography": "Level",
      "Utilities": ["None Connected", "Electricity Available"],
      "ZoningDescription": "Residential-Single Family",
      "NST_BonusYN": "No",
      "ListingKey": "NST5154644",
      "ModificationTimestamp": "2023-06-25T05:02:03.624Z",
      "PhotosChangeTimestamp": "2022-05-14T20:33:03.360Z",
      "OriginatingSystemName": "northstar",
      "Media": [
        {
          "Order": 1,
          "MediaObjectID": "1",
          "LongDescription": "Twin Oaks Loop W. Lot 1 Blk 2",
          "ImageWidth": 1489,
          "ImageHeight": 1446,
          "ImageSizeDescription": "1489x1446",
          "MediaURL": "https://s3.amazonaws.com/mlsgrid/images/ebfe1b34-4b4c-4982-a13a-96f66d51123e.jpeg",
          "MediaModificationTimestamp": "2022-05-14T20:32:26.481Z",
          "MediaKey": "628011da27d73d7935caa4ea"
        }
      ],
      "MlgCanView": false
    }
  ],
  "@odata.nextLink": "https://api.mlsgrid.com/v2/Property?$filter=OriginatingSystemName%20eq%20'northstar'%20and%20StandardStatus%20eq%20enums.StandardStatus'Expired'&$expand=Media%2CRooms%2CUnitTypes&$top=10&$skip=10"
}
